merge_rgba/__init__.py
merge_rgba/scripts/__init__.py
merge_rgba/scripts/cli.py
rio_merge_rgba-0.4.0.dist-info/DESCRIPTION.rst
rio_merge_rgba-0.4.0.dist-info/METADATA
rio_merge_rgba-0.4.0.dist-info/RECORD
rio_merge_rgba-0.4.0.dist-info/WHEEL
rio_merge_rgba-0.4.0.dist-info/entry_points.txt
rio_merge_rgba-0.4.0.dist-info/metadata.json
rio_merge_rgba-0.4.0.dist-info/top_level.txt
