Metadata-Version: 2.0
Name: rio-merge-rgba
Version: 0.4.0
Summary: rio merge alternative optimized for RGBA
Home-page: https://github.com/mapbox/rio-merge-rgba
Author: Matthew Perry
Author-email: perry@mapbox.com
License: MIT
Platform: UNKNOWN
Requires-Dist: click
Requires-Dist: rasterio (>=1.0a12)
Provides-Extra: test
Requires-Dist: pytest; extra == 'test'
Requires-Dist: pytest-cov; extra == 'test'
